{
   "mp": "1.0",
   "sp": "2.0",
   "卡名": "锐流",
   "媒介": [],
   "效果": [
      [
         [
            "特征",
            "启动",
            "行动"
         ],
         [
            "条件",
            [
               "初始区",
               [
                  "绿区"
               ],
               "自己",
               "对象3"
            ],
            [
               "初始对象",
               "对象3",
               "对象3"
            ],
            [
               "取卡牌对象",
               "对象3",
               "是加入蓝区",
               "1",
               "1"
            ],
            [
               "初始区",
               [
                  "蓝区"
               ],
               "自己",
               "对象4"
            ],
            [
               "加入",
               "对象3",
               "对象4"
            ]
         ],
         [
            "初始区",
            [
               "手牌"
            ],
            "自己",
            "对象3"
         ],
         [
            "初始对象",
            "对象3",
            "对象3"
         ],
         [
            "逐一",
            "对象3",
            [
               "以数据为对象",
               "对象3",
               "有效卡名",
               "对象4"
            ],
            [
               "数据判断",
               "对象4",
               "包含",
               "流"
            ],
            [
               "对象处理",
               "对象5",
               "加",
               "对象3"
            ]
         ],
         [
            "计算数量",
            "对象5",
            "对象3"
         ],
         [
            "改变可视数据",
            "对象0",
            "sp",
            "加",
            "对象3",
            "对象0"
         ]
      ],
      [
         [
            "特征",
            "触发",
            "行动"
         ],
         [
            "临时buff",
            "攻击",
            [
               "数据判断",
               "对象0",
               "相等",
               "对象2"
            ]
         ],
         [
            "初始区",
            [
               "行动"
            ],
            "攻击目标",
            "对象3"
         ],
         [
            "初始对象",
            "对象3",
            "对象3"
         ],
         [
            "逐一",
            "对象3",
            [
               "以数据为对象",
               "对象3",
               "sp",
               "对象4"
            ],
            [
               "对象处理",
               "对象5",
               "加",
               "对象4"
            ]
         ],
         [
            "初始区",
            [
               "白区"
            ],
            "自己",
            "对象3"
         ],
         [
            "初始对象",
            "对象3",
            "对象3"
         ],
         [
            "非条件卡牌筛选",
            "对象3",
            "顺序",
            "对象5"
         ],
         [
            "反转",
            "对象3"
         ],
         [
            "取卡牌对象",
            "对象3",
            "是要加入绿区的",
            "1",
            "1"
         ],
         [
            "初始区",
            [
               "绿区"
            ],
            "自己",
            "对象4"
         ],
         [
            "加入",
            "对象3",
            "对象4"
         ]
      ],
      [
         [
            "特征",
            "蓝区",
            "触发"
         ],
         [
            "临时buff",
            "加入",
            [
               "数据判断",
               "对象0",
               "相等",
               "对象2"
            ]
         ],
         [
            "重复",
            "99",
            [
               "初始区",
               [
                  "白区"
               ],
               "自己",
               "对象3"
            ],
            [
               "初始对象",
               "对象3",
               "对象3"
            ],
            [
               "非条件卡牌筛选",
               "对象3",
               "顺序",
               "1"
            ],
            [
               "反转",
               "对象3"
            ],
            [
               "初始区",
               [
                  "绿区"
               ],
               "自己",
               "对象4"
            ],
            [
               "加入",
               "对象3",
               "对象4"
            ],
            [
               "如果",
               [
                  "以数据为对象",
                  "对象3",
                  "组",
                  "对象4"
               ],
               [
                  "否定",
                  [
                     "数据判断",
                     "对象4",
                     "包含",
                     "潮汐"
                  ]
               ],
               [
                  "终止处理",
                  "循环"
               ]
            ]
         ]
      ],
      [
         [
            "特征",
            "绿区"
         ],
         [
            "条件",
            [
               "初始区",
               [
                  "手牌",
                  "场上"
               ],
               "自己",
               "对象3"
            ],
            [
               "初始对象",
               "对象3",
               "对象3"
            ],
            [
               "逐一",
               "对象3",
               [
                  "以数据为对象",
                  "对象3",
                  "有效卡名",
                  "对象4"
               ],
               [
                  "数据判断",
                  "对象4",
                  "包含",
                  "流"
               ],
               [
                  "对象处理",
                  "对象5",
                  "加",
                  "对象3"
               ]
            ],
            [
               "取卡牌对象",
               "对象5",
               "是要破坏的",
               "1",
               "1"
            ],
            [
               "破坏",
               "对象5"
            ]
         ],
         [
            "以数据为对象",
            "对象5",
            "sp",
            "对象3"
         ],
         [
            "改变可视数据",
            "对象0",
            "sp",
            "加",
            "对象3",
            "对象0"
         ]
      ]
   ],
   "文本": "①启动：选绿区的一张牌加入蓝区，可以发动，自己的sp上升手中卡名包含“流的卡牌的数量\n②触发，行动：自己攻击后可以发动，以攻击目标的行动区的所有卡的sp之和为数量，将自己白区上方的等量卡翻开，选一张加入绿区\n③触发，蓝区：自己加入蓝区时，可以发动，重复【将自己白区上方1张牌翻开，则将其加入绿区，如果不是“潮汐”组，则终止循环】\n④绿区：选自己场上或手牌的一张卡名带“流”的牌破坏，可以发动，自己的sp上升那张卡的sp",
   "特征": [],
   "种类": "攻击",
   "组": [
      "潮汐"
   ]
}